{
    "version_id": 12,
    "status": "DRAFT",
    "name": "workflow_versions_12",
    "entity_type": {
        "id": 3,
        "name": "Entity type3",
        "reference_form": 7
    },
    "reference_form": {
        "id": 7,
        "name": "reference_form"
    },
    "created_at": "2023-02-15T15:03:35.247236Z",
    "updated_at": "2023-02-15T15:03:35.247252Z",
    "follow_ups": [
        {
            "id": 1,
            "order": 0,
            "condition": {
                "and": [
                    {
                        "==": [
                            {
                                "var": "last_name"
                            },
                            "last_name_value"
                        ]
                    }
                ]
            },
            "forms": [
                {
                    "id": 2,
                    "name": "FORM_2"
                }
            ],
            "created_at": "2023-02-01T09:25:14.392639Z",
            "updated_at": "2023-02-01T09:25:14.450216Z"
        },
        {
            "id": 2,
            "order": 1,
            "condition": {
                "and": [
                    {
                        "==": [
                            {
                                "var": "gender"
                            },
                            "male"
                        ]
                    },
                    {
                        "==": [
                            {
                                "var": "entity_group"
                            },
                            "A"
                        ]
                    }
                ]
            },
            "forms": [
                {
                    "id": 3,
                    "name": "FORM_3"
                }
            ],
            "created_at": "2023-01-31T11:04:21.140994Z",
            "updated_at": "2023-02-13T10:39:56.507265Z"
        }
    ]
}